
{
  "header": {
    "reportVersion": 1,
    "event": "Allocation failed - JavaScript heap out of memory",
    "trigger": "FatalError",
    "filename": "report.20210508.133409.10732.0.001.json",
    "dumpEventTime": "2021-05-08T13:34:09Z",
    "dumpEventTimeStamp": "1620464649252",
    "processId": 10732,
    "cwd": "C:\\Users\\USER\\Documents\\myapp",
    "commandLine": [
      "node",
      "scripts/start.js"
    ],
    "nodejsVersion": "v12.16.1",
    "wordSize": 64,
    "arch": "x64",
    "platform": "win32",
    "componentVersions": {
      "node": "12.16.1",
      "v8": "7.8.279.23-node.31",
      "uv": "1.34.0",
      "zlib": "1.2.11",
      "brotli": "1.0.7",
      "ares": "1.15.0",
      "modules": "72",
      "nghttp2": "1.40.0",
      "napi": "5",
      "llhttp": "2.0.4",
      "http_parser": "2.9.3",
      "openssl": "1.1.1d",
      "cldr": "35.1",
      "icu": "64.2",
      "tz": "2019c",
      "unicode": "12.1"
    },
    "release": {
      "name": "node",
      "lts": "Erbium",
      "headersUrl": "https://nodejs.org/download/release/v12.16.1/node-v12.16.1-headers.tar.gz",
      "sourceUrl": "https://nodejs.org/download/release/v12.16.1/node-v12.16.1.tar.gz",
      "libUrl": "https://nodejs.org/download/release/v12.16.1/win-x64/node.lib"
    },
    "osName": "Windows_NT",
    "osRelease": "10.0.18363",
    "osVersion": "Windows 10 Enterprise",
    "osMachine": "x86_64",
    "cpus": [
      {
        "model": "Intel(R) Core(TM) i5-7200U CPU @ 2.50GHz",
        "speed": 2712,
        "user": 101570562,
        "nice": 0,
        "sys": 80456562,
        "idle": 389336375,
        "irq": 8479625
      },
      {
        "model": "Intel(R) Core(TM) i5-7200U CPU @ 2.50GHz",
        "speed": 2712,
        "user": 100863953,
        "nice": 0,
        "sys": 62552781,
        "idle": 407946531,
        "irq": 2275796
      },
      {
        "model": "Intel(R) Core(TM) i5-7200U CPU @ 2.50GHz",
        "speed": 2712,
        "user": 119254890,
        "nice": 0,
        "sys": 68274734,
        "idle": 383833625,
        "irq": 920578
      },
      {
        "model": "Intel(R) Core(TM) i5-7200U CPU @ 2.50GHz",
        "speed": 2712,
        "user": 111042781,
        "nice": 0,
        "sys": 62324187,
        "idle": 397996265,
        "irq": 742218
      }
    ],
    "networkInterfaces": [
      {
        "name": "vpn usa",
        "internal": false,
        "mac": "00:00:00:00:00:00",
        "address": "fe80::f009:c397:54a5:e7f8",
        "netmask": "ffff:ffff:ffff:ffff::",
        "family": "IPv6",
        "scopeid": 60
      },
      {
        "name": "vpn usa",
        "internal": false,
        "mac": "00:00:00:00:00:00",
        "address": "192.168.11.222",
        "netmask": "255.255.255.255",
        "family": "IPv4"
      },
      {
        "name": "Ethernet 4",
        "internal": false,
        "mac": "0a:00:27:00:00:1d",
        "address": "fe80::65bd:aebe:8423:3bde",
        "netmask": "ffff:ffff:ffff:ffff::",
        "family": "IPv6",
        "scopeid": 29
      },
      {
        "name": "Ethernet 4",
        "internal": false,
        "mac": "0a:00:27:00:00:1d",
        "address": "192.168.56.1",
        "netmask": "255.255.255.0",
        "family": "IPv4"
      },
      {
        "name": "Wi-Fi",
        "internal": false,
        "mac": "50:5b:c2:09:c7:f7",
        "address": "fe80::5852:3846:bd8d:e10f",
        "netmask": "ffff:ffff:ffff:ffff::",
        "family": "IPv6",
        "scopeid": 23
      },
      {
        "name": "Wi-Fi",
        "internal": false,
        "mac": "50:5b:c2:09:c7:f7",
        "address": "192.168.1.101",
        "netmask": "255.255.255.0",
        "family": "IPv4"
      },
      {
        "name": "Loopback Pseudo-Interface 1",
        "internal": true,
        "mac": "00:00:00:00:00:00",
        "address": "::1",
        "netmask": "ffff:ffff:ffff:ffff:ffff:ffff:ffff:ffff",
        "family": "IPv6",
        "scopeid": 0
      },
      {
        "name": "Loopback Pseudo-Interface 1",
        "internal": true,
        "mac": "00:00:00:00:00:00",
        "address": "127.0.0.1",
        "netmask": "255.0.0.0",
        "family": "IPv4"
      }
    ],
    "host": "secret-man"
  },
  "javascriptStack": {
    "message": "No stack.",
    "stack": [
      "Unavailable."
    ]
  },
  "nativeStack": [
    {
      "pc": "0x00007ff6ed4819f9",
      "symbol": ""
    },
    {
      "pc": "0x00007ff6ed485e1c",
      "symbol": ""
    },
    {
      "pc": "0x00007ff6ed484dd8",
      "symbol": ""
    },
    {
      "pc": "0x00007ff6ed5834cb",
      "symbol": ""
    },
    {
      "pc": "0x00007ff6edd99f4e",
      "symbol": ""
    },
    {
      "pc": "0x00007ff6edd82021",
      "symbol": ""
    },
    {
      "pc": "0x00007ff6edc4e57c",
      "symbol": ""
    },
    {
      "pc": "0x00007ff6edc2a4d3",
      "symbol": ""
    },
    {
      "pc": "0x00007ff6edc287db",
      "symbol": ""
    },
    {
      "pc": "0x00007ff6edc53d5d",
      "symbol": ""
    },
    {
      "pc": "0x00007ff6edc55a94",
      "symbol": ""
    },
    {
      "pc": "0x00007ff6edc4bb13",
      "symbol": ""
    },
    {
      "pc": "0x00007ff6edc4a184",
      "symbol": ""
    },
    {
      "pc": "0x00007ff6edc71e1f",
      "symbol": ""
    },
    {
      "pc": "0x00007ff6eda9384c",
      "symbol": ""
    },
    {
      "pc": "0x00007ff6ed95b23f",
      "symbol": ""
    },
    {
      "pc": "0x00007ff6eda91c6e",
      "symbol": ""
    },
    {
      "pc": "0x00007ff6ed9961ca",
      "symbol": ""
    },
    {
      "pc": "0x00007ff6ee1e4ddd",
      "symbol": ""
    },
    {
      "pc": "0x00007ff6ee168a73",
      "symbol": ""
    },
    {
      "pc": "0x00000320f075c980",
      "symbol": ""
    }
  ],
  "javascriptHeap": {
    "totalMemory": 123318272,
    "totalCommittedMemory": 123318272,
    "usedMemory": 97526160,
    "availableMemory": 2093353456,
    "memoryLimit": 2197815296,
    "heapSpaces": {
      "read_only_space": {
        "memorySize": 262144,
        "committedMemory": 262144,
        "capacity": 32808,
        "used": 32808,
        "available": 0
      },
      "new_space": {
        "memorySize": 16777216,
        "committedMemory": 16777216,
        "capacity": 8379648,
        "used": 490256,
        "available": 7889392
      },
      "old_space": {
        "memorySize": 79577088,
        "committedMemory": 79577088,
        "capacity": 71698824,
        "used": 71470728,
        "available": 228096
      },
      "code_space": {
        "memorySize": 1740800,
        "committedMemory": 1740800,
        "capacity": 1205888,
        "used": 1205888,
        "available": 0
      },
      "map_space": {
        "memorySize": 3149824,
        "committedMemory": 3149824,
        "capacity": 2681520,
        "used": 2681520,
        "available": 0
      },
      "large_object_space": {
        "memorySize": 21188608,
        "committedMemory": 21188608,
        "capacity": 21100672,
        "used": 21100672,
        "available": 0
      },
      "code_large_object_space": {
        "memorySize": 622592,
        "committedMemory": 622592,
        "capacity": 544288,
        "used": 544288,
        "available": 0
      },
      "new_large_object_space": {
        "memorySize": 0,
        "committedMemory": 0,
        "capacity": 8379648,
        "used": 0,
        "available": 8379648
      }
    }
  },
  "resourceUsage": {
    "userCpuSeconds": 11.062,
    "kernelCpuSeconds": 2.89,
    "cpuConsumptionPercent": 29.6851,
    "maxRss": 174247936,
    "pageFaults": {
      "IORequired": 129991,
      "IONotRequired": 0
    },
    "fsActivity": {
      "reads": 6072,
      "writes": 7
    }
  },
  "libuv": [
  ],
  "environmentVariables": {
    "=C:": "C:\\Users\\USER\\Documents\\myapp",
    "ALLUSERSPROFILE": "C:\\ProgramData",
    "APPDATA": "C:\\Users\\USER\\AppData\\Roaming",
    "BABEL_ENV": "development",
    "CHROME_CRASHPAD_PIPE_NAME": "\\\\.\\pipe\\crashpad_12028_XYEDRRWKTXABJNLJ",
    "COLORTERM": "truecolor",
    "CommonProgramFiles": "C:\\Program Files\\Common Files",
    "CommonProgramFiles(x86)": "C:\\Program Files (x86)\\Common Files",
    "CommonProgramW6432": "C:\\Program Files\\Common Files",
    "COMPUTERNAME": "SECRET-MAN",
    "ComSpec": "C:\\WINDOWS\\system32\\cmd.exe",
    "DriverData": "C:\\Windows\\System32\\Drivers\\DriverData",
    "GIT_ASKPASS": "c:\\Users\\USER\\AppData\\Local\\Programs\\Microsoft VS Code\\resources\\app\\extensions\\git\\dist\\askpass.sh",
    "HOME": "C:\\Users\\USER",
    "HOMEDRIVE": "C:",
    "HOMEPATH": "\\Users\\USER",
    "INIT_CWD": "C:\\Users\\USER\\Documents\\myapp\\src",
    "LANG": "en_US.UTF-8",
    "LOCALAPPDATA": "C:\\Users\\USER\\AppData\\Local",
    "LOGONSERVER": "\\\\SECRET-MAN",
    "NODE": "C:\\Program Files\\nodejs\\node.exe",
    "NODE_ENV": "development",
    "NODE_EXE": "C:\\Program Files\\nodejs\\\\node.exe",
    "NODE_PATH": "",
    "NPM_CLI_JS": "C:\\Program Files\\nodejs\\\\node_modules\\npm\\bin\\npm-cli.js",
    "npm_config_access": "",
    "npm_config_allow_same_version": "",
    "npm_config_also": "",
    "npm_config_always_auth": "",
    "npm_config_argv": "{\"remain\":[],\"cooked\":[\"start\"],\"original\":[\"start\"]}",
    "npm_config_audit": "true",
    "npm_config_audit_level": "low",
    "npm_config_auth_type": "legacy",
    "npm_config_before": "",
    "npm_config_bin_links": "true",
    "npm_config_browser": "",
    "npm_config_ca": "",
    "npm_config_cache": "C:\\Users\\USER\\AppData\\Roaming\\npm-cache",
    "npm_config_cache_lock_retries": "10",
    "npm_config_cache_lock_stale": "60000",
    "npm_config_cache_lock_wait": "10000",
    "npm_config_cache_max": "Infinity",
    "npm_config_cache_min": "10",
    "npm_config_cafile": "",
    "npm_config_cert": "",
    "npm_config_cidr": "",
    "npm_config_color": "true",
    "npm_config_commit_hooks": "true",
    "npm_config_depth": "Infinity",
    "npm_config_description": "true",
    "npm_config_dev": "",
    "npm_config_dry_run": "",
    "npm_config_editor": "notepad.exe",
    "npm_config_engine_strict": "",
    "npm_config_fetch_retries": "2",
    "npm_config_fetch_retry_factor": "10",
    "npm_config_fetch_retry_maxtimeout": "60000",
    "npm_config_fetch_retry_mintimeout": "10000",
    "npm_config_force": "",
    "npm_config_format_package_lock": "true",
    "npm_config_fund": "true",
    "npm_config_git": "git",
    "npm_config_git_tag_version": "true",
    "npm_config_global": "",
    "npm_config_globalconfig": "C:\\Users\\USER\\AppData\\Roaming\\npm\\etc\\npmrc",
    "npm_config_globalignorefile": "C:\\Users\\USER\\AppData\\Roaming\\npm\\etc\\npmignore",
    "npm_config_global_style": "",
    "npm_config_group": "",
    "npm_config_ham_it_up": "",
    "npm_config_heading": "npm",
    "npm_config_https_proxy": "",
    "npm_config_if_present": "",
    "npm_config_ignore_prepublish": "",
    "npm_config_ignore_scripts": "",
    "npm_config_init_author_email": "",
    "npm_config_init_author_name": "",
    "npm_config_init_author_url": "",
    "npm_config_init_license": "ISC",
    "npm_config_init_module": "C:\\Users\\USER\\.npm-init.js",
    "npm_config_init_version": "1.0.0",
    "npm_config_json": "",
    "npm_config_key": "",
    "npm_config_legacy_bundling": "",
    "npm_config_link": "",
    "npm_config_local_address": "",
    "npm_config_loglevel": "notice",
    "npm_config_logs_max": "10",
    "npm_config_long": "",
    "npm_config_maxsockets": "50",
    "npm_config_message": "%s",
    "npm_config_metrics_registry": "https://registry.npmjs.org/",
    "npm_config_node_gyp": "C:\\Program Files\\nodejs\\node_modules\\npm\\node_modules\\node-gyp\\bin\\node-gyp.js",
    "npm_config_node_options": "",
    "npm_config_node_version": "12.16.1",
    "npm_config_noproxy": "",
    "npm_config_offline": "",
    "npm_config_onload_script": "",
    "npm_config_only": "",
    "npm_config_optional": "true",
    "npm_config_otp": "",
    "npm_config_package_lock": "true",
    "npm_config_package_lock_only": "",
    "npm_config_parseable": "",
    "npm_config_prefer_offline": "",
    "npm_config_prefer_online": "",
    "npm_config_prefix": "C:\\Users\\USER\\AppData\\Roaming\\npm",
    "npm_config_preid": "",
    "npm_config_production": "",
    "npm_config_progress": "true",
    "npm_config_proxy": "",
    "npm_config_read_only": "",
    "npm_config_rebuild_bundle": "true",
    "npm_config_registry": "https://registry.npmjs.org/",
    "npm_config_rollback": "true",
    "npm_config_save": "true",
    "npm_config_save_bundle": "",
    "npm_config_save_dev": "",
    "npm_config_save_exact": "",
    "npm_config_save_optional": "",
    "npm_config_save_prefix": "^",
    "npm_config_save_prod": "",
    "npm_config_scope": "",
    "npm_config_scripts_prepend_node_path": "warn-only",
    "npm_config_script_shell": "",
    "npm_config_searchexclude": "",
    "npm_config_searchlimit": "20",
    "npm_config_searchopts": "",
    "npm_config_searchstaleness": "900",
    "npm_config_send_metrics": "",
    "npm_config_shell": "C:\\WINDOWS\\system32\\cmd.exe",
    "npm_config_shrinkwrap": "true",
    "npm_config_sign_git_commit": "",
    "npm_config_sign_git_tag": "",
    "npm_config_sso_poll_frequency": "500",
    "npm_config_sso_type": "oauth",
    "npm_config_strict_ssl": "true",
    "npm_config_tag": "latest",
    "npm_config_tag_version_prefix": "v",
    "npm_config_timing": "",
    "npm_config_tmp": "C:\\Users\\USER\\AppData\\Local\\Temp",
    "npm_config_umask": "0000",
    "npm_config_unicode": "",
    "npm_config_unsafe_perm": "true",
    "npm_config_update_notifier": "true",
    "npm_config_usage": "",
    "npm_config_user": "",
    "npm_config_userconfig": "C:\\Users\\USER\\.npmrc",
    "npm_config_user_agent": "npm/6.13.4 node/v12.16.1 win32 x64",
    "npm_config_version": "",
    "npm_config_versions": "",
    "npm_config_viewer": "browser",
    "npm_execpath": "C:\\Program Files\\nodejs\\node_modules\\npm\\bin\\npm-cli.js",
    "npm_lifecycle_event": "start",
    "npm_lifecycle_script": "node scripts/start.js",
    "npm_node_execpath": "C:\\Program Files\\nodejs\\node.exe",
    "npm_package_babel_presets_0": "react-app",
    "npm_package_browserslist_development_0": "last 1 chrome version",
    "npm_package_browserslist_development_1": "last 1 firefox version",
    "npm_package_browserslist_development_2": "last 1 safari version",
    "npm_package_browserslist_production_0": ">0.2%",
    "npm_package_browserslist_production_1": "not dead",
    "npm_package_browserslist_production_2": "not op_mini all",
    "npm_package_dependencies_axios": "^0.19.2",
    "npm_package_dependencies_babel_eslint": "10.1.0",
    "npm_package_dependencies_babel_jest": "^24.9.0",
    "npm_package_dependencies_babel_loader": "8.1.0",
    "npm_package_dependencies_babel_plugin_named_asset_import": "^0.3.6",
    "npm_package_dependencies_babel_preset_react_app": "^9.1.2",
    "npm_package_dependencies_camelcase": "^5.3.1",
    "npm_package_dependencies_case_sensitive_paths_webpack_plugin": "2.3.0",
    "npm_package_dependencies_dotenv": "8.2.0",
    "npm_package_dependencies_dotenv_expand": "5.1.0",
    "npm_package_dependencies_eslint": "^6.6.0",
    "npm_package_dependencies_eslint_config_react_app": "^5.2.1",
    "npm_package_dependencies_eslint_loader": "3.0.3",
    "npm_package_dependencies_eslint_plugin_flowtype": "4.6.0",
    "npm_package_dependencies_eslint_plugin_import": "2.20.1",
    "npm_package_dependencies_eslint_plugin_jsx_a11y": "6.2.3",
    "npm_package_dependencies_eslint_plugin_react": "7.19.0",
    "npm_package_dependencies_eslint_plugin_react_hooks": "^1.6.1",
    "npm_package_dependencies_file_loader": "4.3.0",
    "npm_package_dependencies_fs_extra": "^8.1.0",
    "npm_package_dependencies_html_webpack_plugin": "4.0.0-beta.11",
    "npm_package_dependencies_identity_obj_proxy": "3.0.0",
    "npm_package_dependencies_jest": "24.9.0",
    "npm_package_dependencies_jest_environment_jsdom_fourteen": "1.0.1",
    "npm_package_dependencies_jest_resolve": "24.9.0",
    "npm_package_dependencies_jest_watch_typeahead": "0.4.2",
    "npm_package_dependencies_mini_css_extract_plugin": "0.9.0",
    "npm_package_dependencies_optimize_css_assets_webpack_plugin": "5.0.3",
    "npm_package_dependencies_pnp_webpack_plugin": "1.6.4",
    "npm_package_dependencies_postcss_flexbugs_fixes": "4.1.0",
    "npm_package_dependencies_postcss_loader": "3.0.0",
    "npm_package_dependencies_postcss_normalize": "8.0.1",
    "npm_package_dependencies_postcss_preset_env": "6.7.0",
    "npm_package_dependencies_postcss_safe_parser": "4.0.1",
    "npm_package_dependencies_prop_types": "^15.7.2",
    "npm_package_dependencies_radium": "^0.26.1",
    "npm_package_dependencies_react": "^16.13.1",
    "npm_package_dependencies_react_addons_css_transition_group": "^15.6.2",
    "npm_package_dependencies_react_app_polyfill": "^1.0.6",
    "npm_package_dependencies_react_dev_utils": "^10.2.1",
    "npm_package_dependencies_react_dom": "^16.13.1",
    "npm_package_dependencies_react_redux": "^7.2.4",
    "npm_package_dependencies_react_router": "^5.2.0",
    "npm_package_dependencies_react_router_dom": "^5.2.0",
    "npm_package_dependencies_react_tabs": "^3.2.0",
    "npm_package_dependencies_redux": "^4.1.0",
    "npm_package_dependencies_redux_thunk": "^2.3.0",
    "npm_package_dependencies_resolve": "1.15.0",
    "npm_package_dependencies_resolve_url_loader": "3.1.1",
    "npm_package_dependencies_sass_loader": "8.0.2",
    "npm_package_dependencies_semver": "6.3.0",
    "npm_package_dependencies_styled_components": "^5.2.3",
    "npm_package_dependencies_terser_webpack_plugin": "2.3.5",
    "npm_package_dependencies_ts_pnp": "1.1.6",
    "npm_package_dependencies_url_loader": "2.3.0",
    "npm_package_dependencies_webpack": "4.42.0",
    "npm_package_dependencies_webpack_dev_server": "3.10.3",
    "npm_package_dependencies_webpack_manifest_plugin": "2.2.0",
    "npm_package_dependencies_workbox_webpack_plugin": "4.3.1",
    "npm_package_dependencies__babel_core": "7.9.0",
    "npm_package_dependencies__svgr_webpack": "4.3.3",
    "npm_package_dependencies__testing_library_jest_dom": "^4.2.4",
    "npm_package_dependencies__testing_library_react": "^9.5.0",
    "npm_package_dependencies__testing_library_user_event": "^7.2.1",
    "npm_package_dependencies__typescript_eslint_eslint_plugin": "^2.10.0",
    "npm_package_dependencies__typescript_eslint_parser": "^2.10.0",
    "npm_package_description": "This project was bootstrapped with [Create React App](https://github.com/facebook/create-react-app).",
    "npm_package_devDependencies_css_loader": "^3.4.2",
    "npm_package_devDependencies_style_loader": "^0.23.1",
    "npm_package_eslintConfig_extends": "react-app",
    "npm_package_gitHead": "0e4151075692970756065bb620b759f012e6908b",
    "npm_package_jest_collectCoverageFrom_0": "src/**/*.{js,jsx,ts,tsx}",
    "npm_package_jest_collectCoverageFrom_1": "!src/**/*.d.ts",
    "npm_package_jest_moduleFileExtensions_0": "web.js",
    "npm_package_jest_moduleFileExtensions_1": "js",
    "npm_package_jest_moduleFileExtensions_2": "web.ts",
    "npm_package_jest_moduleFileExtensions_3": "ts",
    "npm_package_jest_moduleFileExtensions_4": "web.tsx",
    "npm_package_jest_moduleFileExtensions_5": "tsx",
    "npm_package_jest_moduleFileExtensions_6": "json",
    "npm_package_jest_moduleFileExtensions_7": "web.jsx",
    "npm_package_jest_moduleFileExtensions_8": "jsx",
    "npm_package_jest_moduleFileExtensions_9": "node",
    "npm_package_jest_moduleNameMapper__react_native_": "react-native-web",
    "npm_package_jest_moduleNameMapper______module___css_sass_scss__": "identity-obj-proxy",
    "npm_package_jest_roots_0": "<rootDir>/src",
    "npm_package_jest_setupFilesAfterEnv_0": "<rootDir>/src/setupTests.js",
    "npm_package_jest_setupFiles_0": "react-app-polyfill/jsdom",
    "npm_package_jest_testEnvironment": "jest-environment-jsdom-fourteen",
    "npm_package_jest_testMatch_0": "<rootDir>/src/**/__tests__/**/*.{js,jsx,ts,tsx}",
    "npm_package_jest_testMatch_1": "<rootDir>/src/**/*.{spec,test}.{js,jsx,ts,tsx}",
    "npm_package_jest_transformIgnorePatterns_0": "[/\\\\]node_modules[/\\\\].+\\.(js|jsx|ts|tsx)$",
    "npm_package_jest_transformIgnorePatterns_1": "^.+\\.module\\.(css|sass|scss)$",
    "npm_package_jest_transform______css_": "<rootDir>/config/jest/cssTransform.js",
    "npm_package_jest_transform_______js_jsx_ts_tsx__": "<rootDir>/node_modules/babel-jest",
    "npm_package_jest_transform__________js_jsx_ts_tsx_css_json___": "<rootDir>/config/jest/fileTransform.js",
    "npm_package_jest_watchPlugins_0": "jest-watch-typeahead/filename",
    "npm_package_jest_watchPlugins_1": "jest-watch-typeahead/testname",
    "npm_package_name": "myapp",
    "npm_package_private": "true",
    "npm_package_readmeFilename": "README.md",
    "npm_package_scripts_build": "node scripts/build.js",
    "npm_package_scripts_start": "node scripts/start.js",
    "npm_package_scripts_test": "node scripts/test.js",
    "npm_package_version": "0.1.0",
    "NPM_PREFIX_NPM_CLI_JS": "C:\\Users\\USER\\AppData\\Roaming\\npm\\node_modules\\npm\\bin\\npm-cli.js",
    "NUMBER_OF_PROCESSORS": "4",
    "OneDrive": "C:\\Users\\USER\\OneDrive",
    "OneDriveConsumer": "C:\\Users\\USER\\OneDrive",
    "ORIGINAL_XDG_CURRENT_DESKTOP": "undefined",
    "OS": "Windows_NT",
    "Path": "C:\\Program Files\\nodejs\\node_modules\\npm\\node_modules\\npm-lifecycle\\node-gyp-bin;C:\\Users\\USER\\Documents\\myapp\\node_modules\\.bin;C:\\Windows\\system32;C:\\Windows;C:\\Windows\\System32\\Wbem;C:\\Windows\\System32\\WindowsPowerShell\\v1.0\\;C:\\Program Files (x86)\\NVIDIA Corporation\\PhysX\\Common;C:\\WINDOWS\\system32;C:\\WINDOWS;C:\\WINDOWS\\System32\\Wbem;C:\\WINDOWS\\System32\\WindowsPowerShell\\v1.0\\;C:\\WINDOWS\\System32\\OpenSSH\\;C:\\Program Files\\nodejs\\;C:\\Program Files\\Git\\cmd;C:\\Users\\USER\\AppData\\Local\\Microsoft\\WindowsApps;C:\\Users\\USER\\AppData\\Roaming\\npm;C:\\Users\\USER\\AppData\\Local\\Programs\\Microsoft VS Code\\bin",
    "PATHEXT": ".COM;.EXE;.BAT;.CMD;.VBS;.VBE;.JS;.JSE;.WSF;.WSH;.MSC",
    "PROCESSOR_ARCHITECTURE": "AMD64",
    "PROCESSOR_IDENTIFIER": "Intel64 Family 6 Model 142 Stepping 9, GenuineIntel",
    "PROCESSOR_LEVEL": "6",
    "PROCESSOR_REVISION": "8e09",
    "ProgramData": "C:\\ProgramData",
    "ProgramFiles": "C:\\Program Files",
    "ProgramFiles(x86)": "C:\\Program Files (x86)",
    "ProgramW6432": "C:\\Program Files",
    "PROMPT": "$P$G",
    "PSModulePath": "C:\\WINDOWS\\system32\\WindowsPowerShell\\v1.0\\Modules\\",
    "PUBLIC": "C:\\Users\\Public",
    "SystemDrive": "C:",
    "SystemRoot": "C:\\WINDOWS",
    "TEMP": "C:\\Users\\USER\\AppData\\Local\\Temp",
    "TERM_PROGRAM": "vscode",
    "TERM_PROGRAM_VERSION": "1.56.0",
    "TMP": "C:\\Users\\USER\\AppData\\Local\\Temp",
    "USERDOMAIN": "SECRET-MAN",
    "USERDOMAIN_ROAMINGPROFILE": "SECRET-MAN",
    "USERNAME": "USER",
    "USERPROFILE": "C:\\Users\\USER",
    "VBOX_MSI_INSTALL_PATH": "F:\\vbox\\",
    "VSCODE_GIT_ASKPASS_MAIN": "c:\\Users\\USER\\AppData\\Local\\Programs\\Microsoft VS Code\\resources\\app\\extensions\\git\\dist\\askpass-main.js",
    "VSCODE_GIT_ASKPASS_NODE": "C:\\Users\\USER\\AppData\\Local\\Programs\\Microsoft VS Code\\Code.exe",
    "VSCODE_GIT_IPC_HANDLE": "\\\\.\\pipe\\vscode-git-d0b9564663-sock",
    "WEBPACK_DEV_SERVER": "true",
    "windir": "C:\\WINDOWS",
    "__COMPAT_LAYER": "RunAsAdmin Installer"
  },
  "sharedObjects": [
    "C:\\Program Files\\nodejs\\node.exe",
    "C:\\WINDOWS\\SYSTEM32\\ntdll.dll",
    "C:\\WINDOWS\\System32\\KERNEL32.DLL",
    "C:\\WINDOWS\\System32\\KERNELBASE.dll",
    "C:\\WINDOWS\\SYSTEM32\\apphelp.dll",
    "C:\\WINDOWS\\System32\\WS2_32.dll",
    "C:\\WINDOWS\\System32\\RPCRT4.dll",
    "C:\\WINDOWS\\System32\\PSAPI.DLL",
    "C:\\WINDOWS\\SYSTEM32\\dbghelp.dll",
    "C:\\WINDOWS\\System32\\ADVAPI32.dll",
    "C:\\WINDOWS\\System32\\ucrtbase.dll",
    "C:\\WINDOWS\\System32\\msvcrt.dll",
    "C:\\WINDOWS\\System32\\sechost.dll",
    "C:\\WINDOWS\\System32\\USER32.dll",
    "C:\\WINDOWS\\SYSTEM32\\IPHLPAPI.DLL",
    "C:\\WINDOWS\\System32\\win32u.dll",
    "C:\\WINDOWS\\SYSTEM32\\USERENV.dll",
    "C:\\WINDOWS\\System32\\GDI32.dll",
    "C:\\WINDOWS\\System32\\gdi32full.dll",
    "C:\\WINDOWS\\System32\\profapi.dll",
    "C:\\WINDOWS\\System32\\msvcp_win.dll",
    "C:\\WINDOWS\\System32\\CRYPT32.dll",
    "C:\\WINDOWS\\System32\\MSASN1.dll",
    "C:\\WINDOWS\\System32\\bcrypt.dll",
    "C:\\WINDOWS\\SYSTEM32\\WINMM.dll",
    "C:\\WINDOWS\\SYSTEM32\\winmmbase.dll",
    "C:\\WINDOWS\\System32\\cfgmgr32.dll",
    "C:\\WINDOWS\\System32\\bcryptPrimitives.dll",
    "C:\\WINDOWS\\System32\\IMM32.DLL",
    "C:\\WINDOWS\\System32\\powrprof.dll",
    "C:\\WINDOWS\\System32\\UMPDC.dll",
    "C:\\WINDOWS\\SYSTEM32\\CRYPTBASE.DLL",
    "C:\\WINDOWS\\system32\\uxtheme.dll",
    "C:\\WINDOWS\\System32\\combase.dll",
    "C:\\WINDOWS\\system32\\mswsock.dll",
    "C:\\WINDOWS\\System32\\kernel.appcore.dll",
    "C:\\WINDOWS\\System32\\NSI.dll",
    "C:\\WINDOWS\\SYSTEM32\\dhcpcsvc6.DLL",
    "C:\\WINDOWS\\SYSTEM32\\dhcpcsvc.DLL",
    "C:\\WINDOWS\\SYSTEM32\\DNSAPI.dll",
    "C:\\WINDOWS\\system32\\napinsp.dll",
    "C:\\WINDOWS\\system32\\pnrpnsp.dll",
    "C:\\WINDOWS\\System32\\winrnr.dll",
    "C:\\WINDOWS\\system32\\NLAapi.dll",
    "C:\\WINDOWS\\system32\\wshbth.dll",
    "C:\\Windows\\System32\\rasadhlp.dll",
    "C:\\WINDOWS\\System32\\fwpuclnt.dll"
  ]
}